setup.py
wales/__init__.py
wales.egg-info/PKG-INFO
wales.egg-info/SOURCES.txt
wales.egg-info/dependency_links.txt
wales.egg-info/not-zip-safe
wales.egg-info/top_level.txt