Metadata-Version: 1.0
Name: wales
Version: 0.1
Summary: Euro2016
Home-page: UNKNOWN
Author: Euro Boys
Author-email: imagingdave@gmail.com
License: MIT
Platform: UNKNOWN
